{
  "intro": "本籤集取自廣澤尊王「大孝成神」之精神，結合《覺世真經》訓誨與當代人生境遇而成，僅供信眾靜心反思、追求孝親濟世之美德。",
  "items": [
    { "no": "第一籤", "title": "孝親無價", "verse": "晨昏定省莫遺忘\n寸草春暉感報長\n但得高堂常歡笑\n人間第一福綿長", "modern": "再忙也要記得問候父母長輩。陪伴與一句問安，比任何金錢禮物都珍貴。今日宜：打通電話回家。" },
    { "no": "第二籤", "title": "善念隨身", "verse": "一念存仁萬事祥\n善心常作福相當\n莫因善小而不為\n積德如山日漸長", "modern": "別小看微小的善意。一個讓座、一個微笑、一次幫忙，都會為你累積看不見的福報。" },
    { "no": "第三籤", "title": "靜心養性", "verse": "怒火攻心須暫忍\n三思而後話自輕\n清風明月隨心轉\n靜處方能見性真", "modern": "近期事情多、人多嘴雜，先深呼吸再回應。今日宜安靜，避免衝動決定。" },
    { "no": "第四籤", "title": "扶弱濟貧", "verse": "見人困苦伸援手\n莫問前因論短長\n善舉如燈傳萬戶\n光明世界共輝煌", "modern": "看見有人需要幫忙，伸出手就對了。你的一份心意，可能是他人最大的依靠。" },
    { "no": "第五籤", "title": "勤勉自強", "verse": "天道酬勤豈虛言\n半畝耕耘半畝甜\n莫嘆時運未開朗\n春暖花開只待緣", "modern": "正在累積中，現在看不見成果別灰心。繼續做下去，時機到了花自然會開。" },
    { "no": "第六籤", "title": "誠信為本", "verse": "一諾千金重於山\n人前人後一般言\n世間最貴是誠信\n莫使心田有暗瞞", "modern": "答應的事情要做到，言行一致最重要。不要為了短期利益失了長遠的信譽。" },
    { "no": "第七籤", "title": "知足常樂", "verse": "貪心無底苦海深\n知足心安福自臨\n簡單清茶亦甘美\n何須山珍與海味", "modern": "不要一直比較，看看自己已經擁有的。今日宜清淡、簡單，學會欣賞當下的小確幸。" },
    { "no": "第八籤", "title": "化解恩怨", "verse": "怨憎之心如毒蜂\n螫人之前先螫己\n一笑泯卻萬重愁\n寬心方有春風起", "modern": "心裡有結，最痛的其實是自己。試著放下，原諒不是為了別人，是為了釋放你自己。" },
    { "no": "第九籤", "title": "學業精進", "verse": "書中自有真道理\n勤讀方知世事明\n寒窗十載非空過\n他日金榜題姓名", "modern": "讀書、進修中的你不會白費。基礎打穩，未來機會來時你才接得住。" },
    { "no": "第十籤", "title": "貴人相助", "verse": "山窮水盡疑無路\n柳暗花明又一村\n貴人暗助行善處\n莫忘當初一念仁", "modern": "近期會遇到願意幫你的人——因為你過去也曾幫過別人。善的循環現在開始收穫。" },
    { "no": "第十一籤", "title": "夫妻和合", "verse": "同船共渡幾世修\n莫為小事起風波\n互相體諒方為愛\n白頭偕老共笑歌", "modern": "夫妻、伴侶間最近多包容。床頭吵床尾和，沒什麼事比兩人的感情重要。" },
    { "no": "第十二籤", "title": "子女平安", "verse": "兒孫自有兒孫福\n莫為兒孫做馬牛\n身教重於千言語\n以身作則樂無憂", "modern": "對孩子放心一點，他們會找到自己的路。比起嘮叨，你的身教才是最深的影響。" },
    { "no": "第十三籤", "title": "事業順遂", "verse": "腳踏實地步步穩\n誠心待人事事通\n莫想一步登天闕\n細水長流自然豐", "modern": "事業要穩紮穩打，不要想著一夕致富。誠信待人、踏實做事，自然會慢慢豐厚。" },
    { "no": "第十四籤", "title": "健康安康", "verse": "病從口入慎飲食\n勿熬夜兮損元神\n身體乃為心之舍\n養生先養一片心", "modern": "身體是心的房子。今日宜早睡、清淡飲食。健康從每一個小選擇累積。" },
    { "no": "第十五籤", "title": "出外平安", "verse": "出門先告父母知\n路上謙和禮自隨\n神明護佑行善者\n旅途平安喜歸來", "modern": "出門在外平安最重要。記得告訴家人去向，待人有禮，便能逢凶化吉。" },
    { "no": "第十六籤", "title": "謙卑受教", "verse": "三人行兮必有師\n謙者如海納百川\n滿招損兮謙受益\n虛心方能得真傳", "modern": "別覺得自己什麼都懂，多聽別人說話。最有智慧的人，總是最謙卑的人。" },
    { "no": "第十七籤", "title": "錢財有度", "verse": "君子愛財取有道\n非分之財不可貪\n勤儉持家家業旺\n莫使錢財害心安", "modern": "錢要賺得心安，不取不義之財。勤儉、量入為出，財運才會穩定長久。" },
    { "no": "第十八籤", "title": "感恩之心", "verse": "受人滴水之恩澤\n當思湧泉以報之\n感恩心起福自來\n忘恩負義禍不離", "modern": "想想曾經幫過你的人，找個機會回報、或把善意傳遞下去。感恩是最好的功課。" },
    { "no": "第十九籤", "title": "誤會冰釋", "verse": "鏡花水月皆虛妄\n莫信讒言起紛爭\n當面說清便明白\n一笑置之又何妨", "modern": "聽到八卦、流言，不要急著相信或動怒。直接溝通，誤會自然化解。" },
    { "no": "第二十籤", "title": "節制有方", "verse": "酒色財氣四堵牆\n人皆能跳是仙人\n適可而止無傷害\n貪歡作樂禍上身", "modern": "凡事適可而止，享樂不過度。今日宜自律、節制——這正是長久幸福的基礎。" },
    { "no": "第二十一籤", "title": "團圓和樂", "verse": "天倫之樂勝千金\n圍爐共敘話家常\n莫讓事業誤親情\n生命中誰最重要", "modern": "再忙也要留時間給家人。事業可以重來，但親人陪伴的時光錯過就不再。" },
    { "no": "第二十二籤", "title": "守口如瓶", "verse": "禍從口出言宜慎\n是非之地少停留\n他人秘事莫宣揚\n口德修成福自有", "modern": "別人的事情少議論，秘密更要守得住。沉默有時候比說話更有力量。" },
    { "no": "第二十三籤", "title": "勇敢承擔", "verse": "事到臨頭莫退縮\n承擔責任顯丈夫\n推諉卸責失人格\n挺身而出見真情", "modern": "遇到問題要面對，不要躲。承擔得起的人，才贏得他人的信任與尊敬。" },
    { "no": "第二十四籤", "title": "孝悌之道", "verse": "兄友弟恭家興旺\n姊妹和合似一身\n父母最樂看此景\n手足同心力斷金", "modern": "兄弟姊妹之間多體諒。家人和睦，才是父母最大的安慰與祝福。" },
    { "no": "第二十五籤", "title": "禍福相依", "verse": "塞翁失馬焉知禍\n人間悲喜本無常\n隨遇而安心自寬\n是福是禍莫衡量", "modern": "好事壞事都有它的道理，當下別急著評論。隨遇而安，心自然開闊。" },
    { "no": "第二十六籤", "title": "教育子女", "verse": "養不教兮父之過\n嚴慈相濟育英才\n陪伴成長最珍貴\n莫等失去空徘徊", "modern": "教孩子需要陪伴與耐心，嚴慈並行。陪伴的時光是金錢買不回的。" },
    { "no": "第二十七籤", "title": "回頭是岸", "verse": "迷途知返尚未晚\n苦海無邊勇回頭\n放下執著心開朗\n光明大道在前頭", "modern": "如果走錯路，現在回頭都還來得及。放下執著，海闊天空就在轉念之間。" },
    { "no": "第二十八籤", "title": "結善緣", "verse": "廣結善緣福田種\n人海茫茫遇便緣\n一句問候勝萬語\n善意如花處處春", "modern": "今日宜與人結好緣。一句問候、一個微笑，可能就是你和某人緣分的開始。" },
    { "no": "第二十九籤", "title": "靜以致遠", "verse": "寧靜致遠淡泊志\n莫被名利亂心懷\n清心寡欲身自輕\n大道無聲入心來", "modern": "近期不要追逐太多東西，學會獨處與沉澱。靜下來，反而能看見更遠的方向。" },
    { "no": "第三十籤", "title": "尊王垂佑", "verse": "尊王孝義感天地\n護佑善人合家安\n但求自身行端正\n吉星高照福無邊", "modern": "你心存善念、行得正、做得直，自然有神明庇佑。今日宜回家陪伴家人，這就是最大的福氣。" }
  ]
}
